kaniko_deploy/__init__.py
kaniko_deploy/__main__.py
kaniko_deploy/main.py
tests/__init__.py
tests/test_main.py
kaniko_deploy-1.2.dist-info/LICENSE
kaniko_deploy-1.2.dist-info/METADATA
kaniko_deploy-1.2.dist-info/WHEEL
kaniko_deploy-1.2.dist-info/entry_points.txt
kaniko_deploy-1.2.dist-info/top_level.txt
kaniko_deploy-1.2.dist-info/RECORD
