Metadata-Version: 2.1
Name: kaniko_deploy
Version: 1.2
Author-email: nurdslab99@gmail.com
License: MIT
Requires-Python: >=3.12
License-File: LICENSE
Requires-Dist: black ==24.8.0
Requires-Dist: build ==1.2.1
Requires-Dist: cachetools ==5.4.0
Requires-Dist: certifi ==2024.7.4
Requires-Dist: charset-normalizer ==3.3.2
Requires-Dist: click ==8.1.7
Requires-Dist: colorama ==0.4.6
Requires-Dist: docutils ==0.21.2
Requires-Dist: google-auth ==2.33.0
Requires-Dist: idna ==3.7
Requires-Dist: importlib-metadata ==8.2.0
Requires-Dist: iniconfig ==2.0.0
Requires-Dist: jaraco.classes ==3.4.0
Requires-Dist: jaraco.context ==5.3.0
Requires-Dist: jaraco.functools ==4.0.2
Requires-Dist: keyring ==25.3.0
Requires-Dist: kubernetes ==30.1.0
Requires-Dist: markdown-it-py ==3.0.0
Requires-Dist: mdurl ==0.1.2
Requires-Dist: more-itertools ==10.4.0
Requires-Dist: mypy-extensions ==1.0.0
Requires-Dist: nh3 ==0.2.18
Requires-Dist: oauthlib ==3.2.2
Requires-Dist: packaging ==24.1
Requires-Dist: pathspec ==0.12.1
Requires-Dist: pkginfo ==1.10.0
Requires-Dist: platformdirs ==4.2.2
Requires-Dist: pluggy ==1.5.0
Requires-Dist: pyasn1 ==0.6.0
Requires-Dist: pyasn1-modules ==0.4.0
Requires-Dist: Pygments ==2.18.0
Requires-Dist: pyproject-hooks ==1.1.0
Requires-Dist: pytest ==8.3.2
Requires-Dist: python-dateutil ==2.9.0.post0
Requires-Dist: pywin32-ctypes ==0.2.2
Requires-Dist: PyYAML ==6.0.2
Requires-Dist: readme-renderer ==44.0
Requires-Dist: requests ==2.32.3
Requires-Dist: requests-oauthlib ==2.0.0
Requires-Dist: requests-toolbelt ==1.0.0
Requires-Dist: rfc3986 ==2.0.0
Requires-Dist: rich ==13.7.1
Requires-Dist: rsa ==4.9
Requires-Dist: setuptools ==72.1.0
Requires-Dist: six ==1.16.0
Requires-Dist: twine ==5.1.1
Requires-Dist: urllib3 ==2.2.2
Requires-Dist: websocket-client ==1.8.0
Requires-Dist: zipp ==3.19.2
